vsensebox/__init__.py
vsensebox/config/__init__.py
vsensebox/config/confighelper.py
vsensebox/config/configurator.py
vsensebox/config/strings.py
vsensebox/config/datasets/.gitignore
vsensebox/config/detectors/default.yaml
vsensebox/config/detectors/detectors.zip
vsensebox/config/detectors/yolo_classic_v3tiny.yaml
vsensebox/config/detectors/yolo_classic_v4tiny.yaml
vsensebox/config/detectors/yolo_ultralytics_v10n.yaml
vsensebox/config/detectors/yolo_ultralytics_v10s.yaml
vsensebox/config/detectors/yolo_ultralytics_v11n.yaml
vsensebox/config/detectors/yolo_ultralytics_v11s.yaml
vsensebox/config/detectors/yolo_ultralytics_v3tinyu.yaml
vsensebox/config/detectors/yolo_ultralytics_v5nu.yaml
vsensebox/config/detectors/yolo_ultralytics_v5su.yaml
vsensebox/config/detectors/yolo_ultralytics_v8n.yaml
vsensebox/config/detectors/yolo_ultralytics_v8s.yaml
vsensebox/config/detectors/yolo_ultralytics_v9s.yaml
vsensebox/config/detectors/yolo_ultralytics_v9t.yaml
vsensebox/config/strings/strings.yaml
vsensebox/config/strings/strings.zip
vsensebox/config/trackers/basiciou.yaml
vsensebox/config/trackers/centroid.yaml
vsensebox/config/trackers/deepsort.yaml
vsensebox/config/trackers/default.yaml
vsensebox/config/trackers/sort.yaml
vsensebox/config/trackers/trackers.zip
vsensebox/data/__init__.py
vsensebox/data/converter.py
vsensebox/data/dataset.py
vsensebox/data/datasets/.gitignore
vsensebox/data/detectors/.gitignore
vsensebox/data/logs/.gitignore
vsensebox/data/trackers/.gitignore
vsensebox/gui/__init__.py
vsensebox/gui/cfgloader_ui.py
vsensebox/gui/uitools.py
vsensebox/gui/assets/settings.ico
vsensebox/modules/__init__.py
vsensebox/modules/detectors/__init__.py
vsensebox/modules/detectors/detectors.py
vsensebox/modules/detectors/yolo_classic.py
vsensebox/modules/detectors/yolo_ultralytics.py
vsensebox/modules/trackers/__init__.py
vsensebox/modules/trackers/basiciou.py
vsensebox/modules/trackers/centroid.py
vsensebox/modules/trackers/deepsort.py
vsensebox/modules/trackers/sort.py
vsensebox-0.4.1.dist-info/LICENSE
vsensebox-0.4.1.dist-info/METADATA
vsensebox-0.4.1.dist-info/WHEEL
vsensebox-0.4.1.dist-info/top_level.txt
vsensebox-0.4.1.dist-info/RECORD
