Metadata-Version: 2.2
Name: vsensebox
Version: 0.4.1
Summary: VSenseBox - Python toolbox for visual sensing.
Home-page: https://github.com/numediart/vsensebox
Author: Ratha SIV
Maintainer: rathaROG
License: GPL-3.0-or-later
Keywords: Toolbox,Detect,Track,Visual,Sense
Classifier: Development Status :: 4 - Beta
Classifier: Environment :: Console
Classifier: Intended Audience :: Developers
Classifier: Intended Audience :: Education
Classifier: Intended Audience :: Information Technology
Classifier: Intended Audience :: Science/Research
Classifier: License :: OSI Approved :: GNU General Public License v3 or later (GPLv3+)
Classifier: Programming Language :: Python
Classifier: Programming Language :: Python :: 3
Classifier: Programming Language :: Python :: 3 :: Only
Classifier: Programming Language :: Python :: 3.9
Classifier: Programming Language :: Python :: 3.10
Classifier: Programming Language :: Python :: 3.11
Classifier: Programming Language :: Python :: 3.12
Classifier: Topic :: Scientific/Engineering
Classifier: Topic :: Scientific/Engineering :: Image Recognition
Classifier: Topic :: Software Development
Classifier: Operating System :: Microsoft :: Windows
Classifier: Operating System :: POSIX
Classifier: Operating System :: Unix
Classifier: Operating System :: MacOS
Requires-Python: >=3.9
License-File: LICENSE
Requires-Dist: Cython>=0.29.37
Requires-Dist: numpy
Requires-Dist: opencv-contrib-python
Requires-Dist: scikit-image
Requires-Dist: scipy>=1.10.0
Requires-Dist: pandas
Requires-Dist: Pillow
Requires-Dist: psutil
Requires-Dist: tqdm
Requires-Dist: matplotlib
Requires-Dist: PyYAML
Requires-Dist: future
Requires-Dist: protobuf
Requires-Dist: tensorflow
Requires-Dist: torch
Requires-Dist: torchvision
Requires-Dist: filterpy
Requires-Dist: lapx>=0.5.11
Requires-Dist: PyQt6
Requires-Dist: vsensebox-ultralytics>=8.3.5
Requires-Dist: sfps
Dynamic: author
Dynamic: classifier
Dynamic: description
Dynamic: description-content-type
Dynamic: home-page
Dynamic: keywords
Dynamic: license
Dynamic: maintainer
Dynamic: requires-dist
Dynamic: requires-python
Dynamic: summary
